README.rst
setup.py
djangorestframework_chain.egg-info/PKG-INFO
djangorestframework_chain.egg-info/SOURCES.txt
djangorestframework_chain.egg-info/dependency_links.txt
djangorestframework_chain.egg-info/requires.txt
djangorestframework_chain.egg-info/top_level.txt
rest_framework_chain/__init__.py
rest_framework_chain/filters.py
rest_framework_chain/filterset.py
rest_framework_chain/models.py
rest_framework_chain/tests.py
rest_framework_chain/__pycache__/__init__.cpython-33.pyc
rest_framework_chain/__pycache__/filters.cpython-33.pyc
rest_framework_chain/__pycache__/filterset.cpython-33.pyc
rest_framework_chain/__pycache__/models.cpython-33.pyc
rest_framework_chain/__pycache__/tests.cpython-33.pyc