Metadata-Version: 1.1
Name: djangorestframework-chain
Version: 0.1.3
Summary: Chained relations and filtering for Django REST Framework
Home-page: http://github.com/philipn/django-rest-framework-chain
Author: Philip Neustrom
Author-email: philipn@gmail.com
License: MIT
Platform: UNKNOWN
Classifier: Development Status :: 5 - Production/Stable
Classifier: Environment :: Web Environment
Classifier: Framework :: Django
Classifier: Intended Audience :: Developers
Classifier: License :: OSI Approved :: BSD License
Classifier: Operating System :: OS Independent
Classifier: Programming Language :: Python
Classifier: Programming Language :: Python :: 3
Classifier: Topic :: Internet :: WWW/HTTP
